<root annotationID="0" passageID="answers-20111108111312AAq4ETn_ans-0035">
  <attributes />
  <extra format="conllu" />
  <layer layerID="0">
    <attributes />
    <extra doc="[[[7859011591137717335, 561228191312463089, 13656873538139661788, 94, 0, 2, 426, 1, 12204527652707022206, 4690420944186131903, 7859011591137717335], [15450463707294738945, 1289836513871212815, 13927759927860985106, 99, 0, 2, 8206900633647566924, 0, 13110060611322374290, 16978132545290669629, 3460455159807539602], [18194338103975822726, 18194338103975822726, 1292078113972184607, 84, 0, 2, 420, 4, 13110060611322374290, 2985121464356781022, 11402152577528684049], [1572612192562026184, 561228191312463089, 4062917326063685704, 83, 0, 2, 437, 1, 13110060611322374290, 9409450202036847209, 17577015140245084783], [7562983679033046312, 7562983679033046312, 15308085513773655218, 91, 0, 2, 426, 2, 4088098365541558500, 8148669997605808657, 7562983679033046312], [14378475389916013800, 14378475389916013800, 16235386156175103506, 99, 0, 2, 402, 1, 4088098365541558500, 646772771845179972, 14378475389916013800], [12488923932015381607, 12488923932015381607, 14200088355797579614, 99, 0, 2, 396, -5, 13110060611322374290, 15598372446745583797, 6388973655490464457], [7831658034963690409, 7831658034963690409, 1292078113972184607, 84, 0, 2, 440, -1, 13110060611322374290, 13110760720460257827, 16701608521236914874], [3899131925553995529, 10382539506755952630, 1534113631682161808, 99, 0, 2, 403, 1, 13110060611322374290, 15598372446745583797, 7679303661980345986], [12510861666511269580, 11499129264984400598, 3822385049556375858, 99, 0, 2, 435, -2, 13110060611322374290, 15817570140490810055, 3746805576453044217], [2593208677638477497, 2593208677638477497, 2593208677638477497, 96, 0, 2, 442, -4, 2593208677638477497, 2593208677638477497, 2593208677638477497], [2283656566040971221, 2283656566040971221, 17571114184892886314, 88, 0, 2, 404, -5, 4088098365541558500, 11901859001352538922, 2283656566040971221], [11532405253426108718, 11532405253426108718, 17109001835818727656, 99, 0, 2, 407, -6, 4088098365541558500, 8861071527689086543, 11532405253426108718], [5640369432778651323, 5640369432778651323, 1292078113972184607, 84, 0, 2, 440, -1, 4370460163704169311, 1489474827855109852, 5640369432778651323], [14969088826861635150, 937856491476774425, 15794550382381185553, 95, 0, 2, 7037928807040764755, 1, 14968597813295776895, 4690420944186131903, 14969088826861635150], [9321776990032145644, 16236707722436152047, 783433942507015291, 91, 0, 2, 413, -3, 13110060611322374290, 13110760720460257827, 17051212862104794208], [3791531372978436496, 3791531372978436496, 5595707737748328492, 93, 0, 2, 402, 1, 4370460163704169311, 15369245168918225700, 3791531372978436496], [17461235395181654430, 17461235395181654430, 14200088355797579614, 99, 0, 2, 396, -5, 13110060611322374290, 15817570140490810055, 472110121363149501], [2661093235354845946, 561228191312463089, 4062917326063685704, 83, 0, 2, 437, 1, 4088098365541558500, 15817570140490810055, 2661093235354845946], [13928622317523333097, 13928622317523333097, 15308085513773655218, 91, 0, 2, 413, -2, 13110060611322374290, 15817570140490810055, 10748144119362648261], [2593208677638477497, 2593208677638477497, 2593208677638477497, 96, 0, 2, 442, -3, 2593208677638477497, 2593208677638477497, 2593208677638477497], [3818676660047855456, 3818676660047855456, 14200088355797579614, 99, 0, 2, 407, -4, 13110060611322374290, 11901859001352538922, 16111258787187009011], [7425985699627899538, 7425985699627899538, 15267657372422890137, 89, 0, 2, 412, 1, 4088098365541558500, 15369245168918225700, 7425985699627899538], [13491131531340830575, 7941236663047931822, 783433942507015291, 91, 0, 2, 413, -2, 13110060611322374290, 11901859001352538922, 9513992237111151098], [14969088826861635150, 937856491476774425, 15794550382381185553, 95, 0, 2, 430, -3, 14968597813295776895, 4690420944186131903, 14969088826861635150], [2593208677638477497, 2593208677638477497, 2593208677638477497, 96, 0, 2, 442, -4, 2593208677638477497, 2593208677638477497, 2593208677638477497], [2283656566040971221, 2283656566040971221, 17571114184892886314, 88, 0, 2, 404, -5, 4088098365541558500, 11901859001352538922, 2283656566040971221], [3791531372978436496, 3791531372978436496, 5595707737748328492, 93, 0, 2, 402, 1, 4370460163704169311, 15369245168918225700, 3791531372978436496], [15159758025291269046, 15159758025291269046, 14200088355797579614, 99, 0, 2, 407, -7, 13110060611322374290, 1720370409040345145, 8717530836033822417], [4380130941430378203, 4380130941430378203, 1292078113972184607, 84, 0, 2, 420, 2, 13110060611322374290, 15369245168918225700, 14949295185858420483], [1655312771067108281, 561228191312463089, 13656873538139661788, 94, 0, 2, 426, 1, 4370460163704169311, 15817570140490810055, 1655312771067108281], [12594746099441336468, 6480458294193393462, 13927759927860985106, 99, 0, 2, 405, -3, 13110060611322374290, 16978132545290669629, 5603553855925065805], [3791531372978436496, 3791531372978436496, 5595707737748328492, 93, 0, 2, 402, 1, 4370460163704169311, 15369245168918225700, 3791531372978436496], [3210859300969447116, 3210859300969447116, 14200088355797579614, 99, 0, 2, 446, -2, 13110060611322374290, 16562859848569467201, 16203534885047373824], [12646065887601541794, 12646065887601541794, 12646065887601541794, 96, 0, 2, 442, -33, 12646065887601541794, 12646065887601541794, 12646065887601541794]]]" />
    <node ID="0.1" type="Word">
      <attributes paragraph="1" paragraph_position="1" text="It" />
      <extra enhanced="2:expl" features="Case=Nom|Gender=Neut|Number=Sing|Person=3|PronType=Prs" frame="_" lemma="it" pos="PRON" tag="PRP" />
    </node>
    <node ID="0.2" type="Word">
      <attributes paragraph="1" paragraph_position="2" text="sounds" />
      <extra enhanced="0:root" features="Mood=Ind|Number=Sing|Person=3|Tense=Pres|VerbForm=Fin" frame="_" lemma="sound" pos="VERB" tag="VBZ" />
    </node>
    <node ID="0.3" type="Word">
      <attributes paragraph="1" paragraph_position="3" text="like" />
      <extra enhanced="7:mark" features="_" frame="_" lemma="like" pos="SCONJ" tag="IN" />
    </node>
    <node ID="0.4" type="Word">
      <attributes paragraph="1" paragraph_position="4" text="your" />
      <extra enhanced="5:nmod:poss" features="Person=2|Poss=Yes|PronType=Prs" frame="_" lemma="you" pos="PRON" tag="PRP$" />
    </node>
    <node ID="0.5" type="Word">
      <attributes paragraph="1" paragraph_position="5" text="dog" />
      <extra enhanced="7:nsubj" features="Number=Sing" frame="_" lemma="dog" pos="NOUN" tag="NN" />
    </node>
    <node ID="0.6" type="Word">
      <attributes paragraph="1" paragraph_position="6" text="may" />
      <extra enhanced="7:aux" features="VerbForm=Fin" frame="_" lemma="may" pos="AUX" tag="MD" />
    </node>
    <node ID="0.7" type="Word">
      <attributes paragraph="1" paragraph_position="7" text="benefit" />
      <extra enhanced="2:advcl:like" features="VerbForm=Inf" frame="_" lemma="benefit" pos="VERB" tag="VB" />
    </node>
    <node ID="0.8" type="Word">
      <attributes paragraph="1" paragraph_position="8" text="from" />
      <extra enhanced="10:mark" features="_" frame="_" lemma="from" pos="SCONJ" tag="IN" />
    </node>
    <node ID="0.9" type="Word">
      <attributes paragraph="1" paragraph_position="9" text="being" />
      <extra enhanced="10:aux:pass" features="VerbForm=Ger" frame="_" lemma="be" pos="AUX" tag="VBG" />
    </node>
    <node ID="0.10" type="Word">
      <attributes paragraph="1" paragraph_position="10" text="hospitalized" />
      <extra enhanced="7:advcl:from" features="Tense=Past|VerbForm=Part|Voice=Pass" frame="_" lemma="hospitalize" pos="VERB" tag="VBN" />
    </node>
    <node ID="0.11" type="Punctuation">
      <attributes paragraph="1" paragraph_position="11" text="," />
      <extra enhanced="13:punct" features="_" frame="_" lemma="," pos="PUNCT" tag="," />
    </node>
    <node ID="0.12" type="Word">
      <attributes paragraph="1" paragraph_position="12" text="and" />
      <extra enhanced="13:cc" features="_" frame="_" lemma="and" pos="CCONJ" tag="CC" />
    </node>
    <node ID="0.13" type="Word">
      <attributes paragraph="1" paragraph_position="13" text="put" />
      <extra enhanced="7:advcl:from|10:conj:and" features="Tense=Past|VerbForm=Part" frame="_" lemma="put" pos="VERB" tag="VBN" />
    </node>
    <node ID="0.14" type="Word">
      <attributes paragraph="1" paragraph_position="14" text="on" />
      <extra enhanced="16:case" features="_" frame="_" lemma="on" pos="ADP" tag="IN" />
    </node>
    <node ID="0.15" type="Word">
      <attributes paragraph="1" paragraph_position="15" text="IV" />
      <extra enhanced="16:compound" features="Number=Sing" frame="_" lemma="iv" pos="NOUN" tag="NN" />
    </node>
    <node ID="0.16" type="Word">
      <attributes paragraph="1" paragraph_position="16" text="fluids" />
      <extra enhanced="13:obl:on" features="Number=Plur" frame="_" lemma="fluid" pos="NOUN" tag="NNS" />
    </node>
    <node ID="0.17" type="Word">
      <attributes paragraph="1" paragraph_position="17" text="to" />
      <extra enhanced="18:mark" features="_" frame="_" lemma="to" pos="PART" tag="TO" />
    </node>
    <node ID="0.18" type="Word">
      <attributes paragraph="1" paragraph_position="18" text="help" />
      <extra enhanced="10:advcl:to" features="VerbForm=Inf" frame="_" lemma="help" pos="VERB" tag="VB" />
    </node>
    <node ID="0.19" type="Word">
      <attributes paragraph="1" paragraph_position="19" text="his" />
      <extra enhanced="20:nmod:poss" features="Gender=Masc|Number=Sing|Person=3|Poss=Yes|PronType=Prs" frame="_" lemma="he" pos="PRON" tag="PRP$" />
    </node>
    <node ID="0.20" type="Word">
      <attributes paragraph="1" paragraph_position="20" text="hydration" />
      <extra enhanced="18:obj" features="Number=Sing" frame="_" lemma="hydration" pos="NOUN" tag="NN" />
    </node>
    <node ID="0.21" type="Punctuation">
      <attributes paragraph="1" paragraph_position="21" text="," />
      <extra enhanced="22:punct" features="_" frame="_" lemma="," pos="PUNCT" tag="," />
    </node>
    <node ID="0.22" type="Word">
      <attributes paragraph="1" paragraph_position="22" text="administer" />
      <extra enhanced="10:advcl:to|18:conj:and" features="VerbForm=Inf" frame="_" lemma="administer" pos="VERB" tag="VB" />
    </node>
    <node ID="0.23" type="Word">
      <attributes paragraph="1" paragraph_position="23" text="the" />
      <extra enhanced="25:det" features="Definite=Def|PronType=Art" frame="_" lemma="the" pos="DET" tag="DT" />
    </node>
    <node ID="0.24" type="Word">
      <attributes paragraph="1" paragraph_position="24" text="antibiotics" />
      <extra enhanced="25:compound" features="Number=Plur" frame="_" lemma="antibiotic" pos="NOUN" tag="NNS" />
    </node>
    <node ID="0.25" type="Word">
      <attributes paragraph="1" paragraph_position="25" text="IV" />
      <extra enhanced="22:obj" features="Number=Sing" frame="_" lemma="iv" pos="NOUN" tag="NN" />
    </node>
    <node ID="0.26" type="Punctuation">
      <attributes paragraph="1" paragraph_position="26" text="," />
      <extra enhanced="29:punct" features="_" frame="_" lemma="," pos="PUNCT" tag="," />
    </node>
    <node ID="0.27" type="Word">
      <attributes paragraph="1" paragraph_position="27" text="and" />
      <extra enhanced="29:cc" features="_" frame="_" lemma="and" pos="CCONJ" tag="CC" />
    </node>
    <node ID="0.28" type="Word">
      <attributes paragraph="1" paragraph_position="28" text="to" />
      <extra enhanced="29:mark" features="_" frame="_" lemma="to" pos="PART" tag="TO" />
    </node>
    <node ID="0.29" type="Word">
      <attributes paragraph="1" paragraph_position="29" text="ensure" />
      <extra enhanced="10:advcl:to|18:conj:and" features="VerbForm=Inf" frame="_" lemma="ensure" pos="VERB" tag="VB" />
    </node>
    <node ID="0.30" type="Word">
      <attributes paragraph="1" paragraph_position="30" text="that" />
      <extra enhanced="32:mark" features="_" frame="_" lemma="that" pos="SCONJ" tag="IN" />
    </node>
    <node ID="0.31" type="Word">
      <attributes paragraph="1" paragraph_position="31" text="he" />
      <extra enhanced="32:nsubj|34:nsubj:xsubj" features="Case=Nom|Gender=Masc|Number=Sing|Person=3|PronType=Prs" frame="_" lemma="he" pos="PRON" tag="PRP" />
    </node>
    <node ID="0.32" type="Word">
      <attributes paragraph="1" paragraph_position="32" text="starts" />
      <extra enhanced="29:ccomp" features="Mood=Ind|Number=Sing|Person=3|Tense=Pres|VerbForm=Fin" frame="_" lemma="start" pos="VERB" tag="VBZ" />
    </node>
    <node ID="0.33" type="Word">
      <attributes paragraph="1" paragraph_position="33" text="to" />
      <extra enhanced="34:mark" features="_" frame="_" lemma="to" pos="PART" tag="TO" />
    </node>
    <node ID="0.34" type="Word">
      <attributes paragraph="1" paragraph_position="34" text="recover" />
      <extra enhanced="32:xcomp" features="VerbForm=Inf" frame="_" lemma="recover" pos="VERB" tag="VB" />
    </node>
    <node ID="0.35" type="Punctuation">
      <attributes paragraph="1" paragraph_position="35" text="." />
      <extra enhanced="2:punct" features="_" frame="_" lemma="." pos="PUNCT" tag="." />
    </node>
  </layer>
  <layer layerID="1">
    <attributes />
    <node ID="1.1" type="FN">
      <attributes />
      <edge toID="1.2" type="head">
        <attributes />
        <category tag="head" />
      </edge>
      <edge toID="1.4" type="mark">
        <attributes />
        <category tag="mark" />
      </edge>
      <edge toID="1.5" type="advcl">
        <attributes />
        <category tag="advcl" />
      </edge>
    </node>
    <node ID="1.2" type="FN">
      <attributes />
      <edge toID="1.3" type="head">
        <attributes />
        <category tag="head" />
      </edge>
      <edge toID="1.7" type="expl">
        <attributes />
        <category tag="expl" />
      </edge>
      <edge toID="1.14" type="U">
        <attributes />
        <category tag="U" />
      </edge>
    </node>
    <node ID="1.3" type="FN">
      <attributes />
      <edge toID="0.2" type="Terminal">
        <attributes />
        <category tag="Terminal" />
      </edge>
    </node>
    <node ID="1.4" type="FN">
      <attributes />
      <edge toID="0.3" type="Terminal">
        <attributes />
        <category tag="Terminal" />
      </edge>
    </node>
    <node ID="1.5" type="FN">
      <attributes />
      <edge toID="1.6" type="head">
        <attributes />
        <category tag="head" />
      </edge>
      <edge toID="1.8" type="nsubj">
        <attributes />
        <category tag="nsubj" />
      </edge>
      <edge toID="1.10" type="aux">
        <attributes />
        <category tag="aux" />
      </edge>
      <edge toID="1.11" type="mark">
        <attributes />
        <category tag="mark" />
      </edge>
      <edge toID="1.12" type="advcl">
        <attributes />
        <category tag="advcl" />
      </edge>
      <edge toID="1.18" type="advcl">
        <attributes remote="True" />
        <category tag="advcl" />
      </edge>
    </node>
    <node ID="1.6" type="FN">
      <attributes />
      <edge toID="0.7" type="Terminal">
        <attributes />
        <category tag="Terminal" />
      </edge>
    </node>
    <node ID="1.7" type="FN">
      <attributes />
      <edge toID="0.1" type="Terminal">
        <attributes />
        <category tag="Terminal" />
      </edge>
    </node>
    <node ID="1.8" type="FN">
      <attributes />
      <edge toID="1.9" type="head">
        <attributes />
        <category tag="head" />
      </edge>
      <edge toID="1.15" type="nmod">
        <attributes />
        <category tag="nmod" />
      </edge>
    </node>
    <node ID="1.9" type="FN">
      <attributes />
      <edge toID="0.5" type="Terminal">
        <attributes />
        <category tag="Terminal" />
      </edge>
    </node>
    <node ID="1.10" type="FN">
      <attributes />
      <edge toID="0.6" type="Terminal">
        <attributes />
        <category tag="Terminal" />
      </edge>
    </node>
    <node ID="1.11" type="FN">
      <attributes />
      <edge toID="0.8" type="Terminal">
        <attributes />
        <category tag="Terminal" />
      </edge>
    </node>
    <node ID="1.12" type="FN">
      <attributes />
      <edge toID="1.13" type="head">
        <attributes />
        <category tag="head" />
      </edge>
      <edge toID="1.16" type="aux">
        <attributes />
        <category tag="aux" />
      </edge>
      <edge toID="1.17" type="cc">
        <attributes />
        <category tag="cc" />
      </edge>
      <edge toID="1.18" type="conj">
        <attributes />
        <category tag="conj" />
      </edge>
      <edge toID="1.20" type="mark">
        <attributes />
        <category tag="mark" />
      </edge>
      <edge toID="1.21" type="advcl">
        <attributes />
        <category tag="advcl" />
      </edge>
      <edge toID="1.28" type="advcl">
        <attributes remote="True" />
        <category tag="advcl" />
      </edge>
      <edge toID="1.31" type="advcl">
        <attributes remote="True" />
        <category tag="advcl" />
      </edge>
    </node>
    <node ID="1.13" type="FN">
      <attributes />
      <edge toID="0.10" type="Terminal">
        <attributes />
        <category tag="Terminal" />
      </edge>
    </node>
    <node ID="1.14" type="PNCT">
      <attributes />
      <edge toID="0.35" type="Terminal">
        <attributes />
        <category tag="Terminal" />
      </edge>
    </node>
    <node ID="1.15" type="FN">
      <attributes />
      <edge toID="0.4" type="Terminal">
        <attributes />
        <category tag="Terminal" />
      </edge>
    </node>
    <node ID="1.16" type="FN">
      <attributes />
      <edge toID="0.9" type="Terminal">
        <attributes />
        <category tag="Terminal" />
      </edge>
    </node>
    <node ID="1.17" type="FN">
      <attributes />
      <edge toID="0.12" type="Terminal">
        <attributes />
        <category tag="Terminal" />
      </edge>
    </node>
    <node ID="1.18" type="FN">
      <attributes />
      <edge toID="1.19" type="head">
        <attributes />
        <category tag="head" />
      </edge>
      <edge toID="1.23" type="U">
        <attributes />
        <category tag="U" />
      </edge>
      <edge toID="1.24" type="obl">
        <attributes />
        <category tag="obl" />
      </edge>
    </node>
    <node ID="1.19" type="FN">
      <attributes />
      <edge toID="0.13" type="Terminal">
        <attributes />
        <category tag="Terminal" />
      </edge>
    </node>
    <node ID="1.20" type="FN">
      <attributes />
      <edge toID="0.17" type="Terminal">
        <attributes />
        <category tag="Terminal" />
      </edge>
    </node>
    <node ID="1.21" type="FN">
      <attributes />
      <edge toID="1.22" type="head">
        <attributes />
        <category tag="head" />
      </edge>
      <edge toID="1.26" type="obj">
        <attributes />
        <category tag="obj" />
      </edge>
      <edge toID="1.28" type="conj">
        <attributes />
        <category tag="conj" />
      </edge>
      <edge toID="1.30" type="cc">
        <attributes />
        <category tag="cc" />
      </edge>
      <edge toID="1.31" type="conj">
        <attributes />
        <category tag="conj" />
      </edge>
    </node>
    <node ID="1.22" type="FN">
      <attributes />
      <edge toID="0.18" type="Terminal">
        <attributes />
        <category tag="Terminal" />
      </edge>
    </node>
    <node ID="1.23" type="PNCT">
      <attributes />
      <edge toID="0.11" type="Terminal">
        <attributes />
        <category tag="Terminal" />
      </edge>
    </node>
    <node ID="1.24" type="FN">
      <attributes />
      <edge toID="1.25" type="head">
        <attributes />
        <category tag="head" />
      </edge>
      <edge toID="1.33" type="case">
        <attributes />
        <category tag="case" />
      </edge>
      <edge toID="1.34" type="compound">
        <attributes />
        <category tag="compound" />
      </edge>
    </node>
    <node ID="1.25" type="FN">
      <attributes />
      <edge toID="0.16" type="Terminal">
        <attributes />
        <category tag="Terminal" />
      </edge>
    </node>
    <node ID="1.26" type="FN">
      <attributes />
      <edge toID="1.27" type="head">
        <attributes />
        <category tag="head" />
      </edge>
      <edge toID="1.35" type="nmod">
        <attributes />
        <category tag="nmod" />
      </edge>
    </node>
    <node ID="1.27" type="FN">
      <attributes />
      <edge toID="0.20" type="Terminal">
        <attributes />
        <category tag="Terminal" />
      </edge>
    </node>
    <node ID="1.28" type="FN">
      <attributes />
      <edge toID="1.29" type="head">
        <attributes />
        <category tag="head" />
      </edge>
      <edge toID="1.36" type="U">
        <attributes />
        <category tag="U" />
      </edge>
      <edge toID="1.37" type="obj">
        <attributes />
        <category tag="obj" />
      </edge>
    </node>
    <node ID="1.29" type="FN">
      <attributes />
      <edge toID="0.22" type="Terminal">
        <attributes />
        <category tag="Terminal" />
      </edge>
    </node>
    <node ID="1.30" type="FN">
      <attributes />
      <edge toID="0.27" type="Terminal">
        <attributes />
        <category tag="Terminal" />
      </edge>
    </node>
    <node ID="1.31" type="FN">
      <attributes />
      <edge toID="1.32" type="head">
        <attributes />
        <category tag="head" />
      </edge>
      <edge toID="1.39" type="U">
        <attributes />
        <category tag="U" />
      </edge>
      <edge toID="1.40" type="mark">
        <attributes />
        <category tag="mark" />
      </edge>
      <edge toID="1.41" type="ccomp">
        <attributes />
        <category tag="ccomp" />
      </edge>
    </node>
    <node ID="1.32" type="FN">
      <attributes />
      <edge toID="0.29" type="Terminal">
        <attributes />
        <category tag="Terminal" />
      </edge>
    </node>
    <node ID="1.33" type="FN">
      <attributes />
      <edge toID="0.14" type="Terminal">
        <attributes />
        <category tag="Terminal" />
      </edge>
    </node>
    <node ID="1.34" type="FN">
      <attributes />
      <edge toID="0.15" type="Terminal">
        <attributes />
        <category tag="Terminal" />
      </edge>
    </node>
    <node ID="1.35" type="FN">
      <attributes />
      <edge toID="0.19" type="Terminal">
        <attributes />
        <category tag="Terminal" />
      </edge>
    </node>
    <node ID="1.36" type="PNCT">
      <attributes />
      <edge toID="0.21" type="Terminal">
        <attributes />
        <category tag="Terminal" />
      </edge>
    </node>
    <node ID="1.37" type="FN">
      <attributes />
      <edge toID="1.38" type="head">
        <attributes />
        <category tag="head" />
      </edge>
      <edge toID="1.43" type="det">
        <attributes />
        <category tag="det" />
      </edge>
      <edge toID="1.44" type="compound">
        <attributes />
        <category tag="compound" />
      </edge>
    </node>
    <node ID="1.38" type="FN">
      <attributes />
      <edge toID="0.25" type="Terminal">
        <attributes />
        <category tag="Terminal" />
      </edge>
    </node>
    <node ID="1.39" type="PNCT">
      <attributes />
      <edge toID="0.26" type="Terminal">
        <attributes />
        <category tag="Terminal" />
      </edge>
    </node>
    <node ID="1.40" type="FN">
      <attributes />
      <edge toID="0.28" type="Terminal">
        <attributes />
        <category tag="Terminal" />
      </edge>
    </node>
    <node ID="1.41" type="FN">
      <attributes />
      <edge toID="1.42" type="head">
        <attributes />
        <category tag="head" />
      </edge>
      <edge toID="1.45" type="mark">
        <attributes />
        <category tag="mark" />
      </edge>
      <edge toID="1.46" type="xcomp">
        <attributes />
        <category tag="xcomp" />
      </edge>
      <edge toID="1.48" type="nsubj">
        <attributes />
        <category tag="nsubj" />
      </edge>
    </node>
    <node ID="1.42" type="FN">
      <attributes />
      <edge toID="0.32" type="Terminal">
        <attributes />
        <category tag="Terminal" />
      </edge>
    </node>
    <node ID="1.43" type="FN">
      <attributes />
      <edge toID="0.23" type="Terminal">
        <attributes />
        <category tag="Terminal" />
      </edge>
    </node>
    <node ID="1.44" type="FN">
      <attributes />
      <edge toID="0.24" type="Terminal">
        <attributes />
        <category tag="Terminal" />
      </edge>
    </node>
    <node ID="1.45" type="FN">
      <attributes />
      <edge toID="0.30" type="Terminal">
        <attributes />
        <category tag="Terminal" />
      </edge>
    </node>
    <node ID="1.46" type="FN">
      <attributes />
      <edge toID="1.47" type="head">
        <attributes />
        <category tag="head" />
      </edge>
      <edge toID="1.48" type="nsubj">
        <attributes remote="True" />
        <category tag="nsubj" />
      </edge>
      <edge toID="1.49" type="mark">
        <attributes />
        <category tag="mark" />
      </edge>
    </node>
    <node ID="1.47" type="FN">
      <attributes />
      <edge toID="0.34" type="Terminal">
        <attributes />
        <category tag="Terminal" />
      </edge>
    </node>
    <node ID="1.48" type="FN">
      <attributes />
      <edge toID="0.31" type="Terminal">
        <attributes />
        <category tag="Terminal" />
      </edge>
    </node>
    <node ID="1.49" type="FN">
      <attributes />
      <edge toID="0.33" type="Terminal">
        <attributes />
        <category tag="Terminal" />
      </edge>
    </node>
  </layer>
</root>
