<root annotationID="0" passageID="reviews-018548-0009">
  <attributes />
  <extra format="conllu" />
  <layer layerID="0">
    <attributes />
    <extra doc="[[[16875582379069451158, 561228191312463089, 13656873538139661788, 94, 0, 2, 426, 1, 13110060611322374290, 15369245168918225700, 6375554876062815730], [2158845516055552166, 2158845516055552166, 9188597074677201817, 99, 0, 2, 8206900633647566924, 0, 4370460163704169311, 8148669997605808657, 2158845516055552166], [4380130941430378203, 4380130941430378203, 15267657372422890137, 89, 0, 2, 412, 2, 13110060611322374290, 15369245168918225700, 14949295185858420483], [16948554243429412012, 16948554243429412012, 10554686591937588953, 83, 0, 2, 399, 1, 13110060611322374290, 260667111241363922, 11258196798982842214], [2473243759842082748, 2473243759842082748, 15308085513773655218, 91, 0, 2, 413, -3, 13110060611322374290, 15369245168918225700, 7679303661980345986], [16318918034475841628, 16318918034475841628, 17524233984504158541, 85, 0, 2, 397, 2, 13110060611322374290, 260667111241363922, 18139757808136603089], [7624161793554793053, 561228191312463089, 13656873538139661788, 94, 0, 2, 426, 1, 4088098365541558500, 9409450202036847209, 7624161793554793053], [7590534004881396, 7590534004881396, 9188597074677201817, 99, 0, 2, 7972625988311165362, -3, 13110060611322374290, 16978132545290669629, 5864527961345014045], [7425985699627899538, 7425985699627899538, 15267657372422890137, 89, 0, 2, 412, 1, 4088098365541558500, 15369245168918225700, 7425985699627899538], [9408421902755474071, 9408421902755474071, 15308085513773655218, 91, 0, 2, 413, -2, 13110060611322374290, 8861071527689086543, 3708556048352852047], [7508752285157982505, 7508752285157982505, 1292078113972184607, 84, 0, 2, 440, -3, 13110060611322374290, 15598372446745583797, 11571764995849485429], [9467212356087175434, 7486875045419418034, 783433942507015291, 91, 0, 2, 436, -1, 13110060611322374290, 2985121464356781022, 7409412530419520829], [886050111519832510, 886050111519832510, 1292078113972184607, 84, 0, 2, 440, -1, 4370460163704169311, 1489474827855109852, 886050111519832510], [17479476687133065248, 17479476687133065248, 15308085513773655218, 91, 0, 2, 436, -1, 13110060611322374290, 16900879642891266615, 17080020411610877296], [16037325823156266367, 16037325823156266367, 1292078113972184607, 84, 0, 2, 440, -3, 4088098365541558500, 13110760720460257827, 16037325823156266367], [13710799475896836168, 13710799475896836168, 98, 98, 0, 2, 404, -4, 13710799475896836168, 13710799475896836168, 13710799475896836168], [4560107979603541987, 4560107979603541987, 8427216679587749980, 92, 394, 3, 407, -5, 4620368362210911820, 602994839685422785, 4560107979603541987], [16947018434234518665, 16947018434234518665, 10554686591937588953, 83, 0, 2, 396, -16, 13110060611322374290, 8148669997605808657, 13906627124797355281], [12646065887601541794, 12646065887601541794, 12646065887601541794, 96, 0, 2, 442, -17, 12646065887601541794, 12646065887601541794, 12646065887601541794]]]" />
    <node ID="0.1" type="Word">
      <attributes paragraph="1" paragraph_position="1" text="they" />
      <extra deprel="nsubj" depth="3" edeps="2:nsubj" enhanced="2:nsubj" feats="Case=Nom|Number=Plur|Person=3|PronType=Prs" features="Case=Nom|Number=Plur|Person=3|PronType=Prs" frame="_" head="2" lemma="they" lextag="O-PRON" misc="null" next_terminal_lower_common_ancestor_category="H" next_terminal_lower_common_ancestor_depth="1" orig_paragraph="1" pos="PRON" remarks="0.127" smwe="null" tag="PRP" upos="PRON" wmwe="null" word="they" xpos="PRP" />
    </node>
    <node ID="0.2" type="Word">
      <attributes paragraph="1" paragraph_position="2" text="do" />
      <extra deprel="root" depth="3" edeps="0:root" enhanced="0:root" feats="Mood=Ind|Tense=Pres|VerbForm=Fin" features="Mood=Ind|Tense=Pres|VerbForm=Fin" frame="_" head="0" lemma="do" lexcat="V" lexlemma="do" lextag="O-V-v.stative" local_toknums="2" misc="null" next_terminal_lower_common_ancestor_category="H" next_terminal_lower_common_ancestor_depth="1" orig_paragraph="1" pos="VERB" remarks="0.128" smwe="null" ss="v.stative" ss2="null" tag="VBP" toknums="128" upos="VERB" wmwe="null" word="do" xpos="VBP" />
    </node>
    <node ID="0.3" type="Word">
      <attributes paragraph="1" paragraph_position="3" text="that" />
      <extra deprel="det" depth="4" edeps="5:det" enhanced="5:det" feats="Number=Sing|PronType=Dem" features="Number=Sing|PronType=Dem" frame="_" head="5" lemma="that" lextag="O-DET" misc="null" next_terminal_lower_common_ancestor_category="A" next_terminal_lower_common_ancestor_depth="2" orig_paragraph="1" pos="DET" remarks="0.129" smwe="null" tag="DT" upos="DET" wmwe="null" word="that" xpos="DT" />
    </node>
    <node ID="0.4" type="Word">
      <attributes paragraph="1" paragraph_position="4" text="whole" />
      <extra deprel="amod" depth="5" edeps="5:amod" enhanced="5:amod" feats="Degree=Pos" features="Degree=Pos" frame="_" head="5" lemma="whole" lextag="O-ADJ" misc="null" next_terminal_lower_common_ancestor_category="E" next_terminal_lower_common_ancestor_depth="3" orig_paragraph="1" pos="ADJ" remarks="0.13" smwe="null" tag="JJ" upos="ADJ" wmwe="null" word="whole" xpos="JJ" />
    </node>
    <node ID="0.5" type="Word">
      <attributes paragraph="1" paragraph_position="5" text="thing" />
      <extra deprel="obj" depth="4" edeps="2:obj" enhanced="2:obj" feats="Number=Sing" features="Number=Sing" frame="_" head="2" lemma="thing" lextag="O-!!@" misc="null" next_terminal_lower_common_ancestor_category="A" next_terminal_lower_common_ancestor_depth="2" orig_paragraph="1" pos="NOUN" remarks="0.131" smwe="null" tag="NN" upos="NOUN" wmwe="null" word="thing" xpos="NN" />
    </node>
    <node ID="0.6" type="Word">
      <attributes paragraph="1" paragraph_position="6" text="where" />
      <extra deprel="advmod" depth="5" edeps="8:advmod" enhanced="8:advmod" feats="PronType=Rel" features="PronType=Rel" frame="_" head="8" lemma="where" lextag="O-ADV" misc="null" next_terminal_lower_common_ancestor_category="E" next_terminal_lower_common_ancestor_depth="3" orig_paragraph="1" pos="ADV" remarks="0.132" smwe="null" tag="WRB" upos="ADV" wmwe="null" word="where" xpos="WRB" />
    </node>
    <node ID="0.7" type="Word">
      <attributes paragraph="1" paragraph_position="7" text="you" />
      <extra deprel="nsubj" depth="5" edeps="8:nsubj" enhanced="8:nsubj" feats="Case=Nom|Person=2|PronType=Prs" features="Case=Nom|Person=2|PronType=Prs" frame="_" head="8" lemma="you" lextag="O-PRON" misc="null" next_terminal_lower_common_ancestor_category="E" next_terminal_lower_common_ancestor_depth="3" orig_paragraph="1" pos="PRON" remarks="0.133" smwe="null" tag="PRP" upos="PRON" wmwe="null" word="you" xpos="PRP" />
    </node>
    <node ID="0.8" type="Word">
      <attributes paragraph="1" paragraph_position="8" text="sandwich" />
      <extra deprel="acl:relcl" depth="5" edeps="5:acl:relcl" enhanced="5:acl:relcl" feats="Mood=Ind|Tense=Pres|VerbForm=Fin" features="Mood=Ind|Tense=Pres|VerbForm=Fin" frame="_" head="5" lemma="sandwich" lexcat="V" lexlemma="sandwich" lextag="O-V-v.contact" local_toknums="8" misc="null" next_terminal_lower_common_ancestor_category="E" next_terminal_lower_common_ancestor_depth="3" orig_paragraph="1" pos="VERB" remarks="0.134" smwe="null" ss="v.contact" ss2="null" tag="VBP" toknums="134" upos="VERB" wmwe="null" word="sandwich" xpos="VBP" />
    </node>
    <node ID="0.9" type="Word">
      <attributes paragraph="1" paragraph_position="9" text="the" />
      <extra deprel="det" depth="6" edeps="10:det" enhanced="10:det" feats="Definite=Def|PronType=Art" features="Definite=Def|PronType=Art" frame="_" head="10" lemma="the" lextag="O-DET" misc="null" next_terminal_lower_common_ancestor_category="A" next_terminal_lower_common_ancestor_depth="4" orig_paragraph="1" pos="DET" remarks="0.135" smwe="null" tag="DT" upos="DET" wmwe="null" word="the" xpos="DT" />
    </node>
    <node ID="0.10" type="Word">
      <attributes paragraph="1" paragraph_position="10" text="pepperoni" />
      <extra deprel="obj" depth="6" edeps="8:obj" enhanced="8:obj" feats="Number=Sing" features="Number=Sing" frame="_" head="8" lemma="pepperoni" lexcat="N" lexlemma="pepperoni" lextag="O-N-n.FOOD" local_toknums="10" misc="null" next_terminal_lower_common_ancestor_category="E" next_terminal_lower_common_ancestor_depth="3" orig_paragraph="1" pos="NOUN" remarks="0.136" smwe="null" ss="n.FOOD" ss2="null" tag="NN" toknums="136" upos="NOUN" wmwe="null" word="pepperoni" xpos="NN" />
    </node>
    <node ID="0.11" type="Word">
      <attributes paragraph="1" paragraph_position="11" text="between" />
      <extra config="default" deprel="case" depth="6" edeps="12:case" enhanced="12:case" feats="null" features="_" frame="_" gov="134" govlemma="sandwich" head="12" lemma="between" lexcat="P" lexlemma="between" lextag="O-P-p.Goal|p.Locus" local_gov="8" local_obj="12" local_toknums="11" misc="null" next_terminal_lower_common_ancestor_category="A" next_terminal_lower_common_ancestor_depth="4" obj="138" objlemma="layer" orig_paragraph="1" pos="ADP" remarks="0.137" smwe="null" ss="p.Goal" ss2="p.Locus" tag="IN" toknums="137" upos="ADP" wmwe="null" word="between" xpos="IN" />
    </node>
    <node ID="0.12" type="Word">
      <attributes paragraph="1" paragraph_position="12" text="layers" />
      <extra deprel="obl" depth="6" edeps="8:obl:between" enhanced="8:obl:between" feats="Number=Plur" features="Number=Plur" frame="_" head="8" lemma="layer" lexcat="N" lexlemma="layer" lextag="O-N-n.COGNITION" local_toknums="12" misc="null" next_terminal_lower_common_ancestor_category="A" next_terminal_lower_common_ancestor_depth="4" orig_paragraph="1" pos="NOUN" remarks="0.138" smwe="null" ss="n.COGNITION" ss2="null" tag="NNS" toknums="138" upos="NOUN" wmwe="null" word="layers" xpos="NNS" />
    </node>
    <node ID="0.13" type="Word">
      <attributes paragraph="1" paragraph_position="13" text="of" />
      <extra config="default" deprel="case" depth="7" edeps="14:case" enhanced="14:case" feats="null" features="_" frame="_" gov="138" govlemma="layer" head="14" lemma="of" lexcat="P" lexlemma="of" lextag="O-P-p.Stuff" local_gov="12" local_obj="14" local_toknums="13" misc="null" next_terminal_lower_common_ancestor_category="E" next_terminal_lower_common_ancestor_depth="5" obj="140" objlemma="cheese" orig_paragraph="1" pos="ADP" remarks="0.139" smwe="null" ss="p.Stuff" ss2="p.Stuff" tag="IN" toknums="139" upos="ADP" wmwe="null" word="of" xpos="IN" />
    </node>
    <node ID="0.14" type="Word">
      <attributes paragraph="1" paragraph_position="14" text="cheese" />
      <extra deprel="nmod" depth="7" edeps="12:nmod:of" enhanced="12:nmod:of" feats="Number=Sing" features="Number=Sing" frame="_" head="12" lemma="cheese" lexcat="N" lexlemma="cheese" lextag="O-N-n.FOOD" local_toknums="14" misc="null" next_terminal_lower_common_ancestor_category="E" next_terminal_lower_common_ancestor_depth="3" orig_paragraph="1" pos="NOUN" remarks="0.14" smwe="null" ss="n.FOOD" ss2="null" tag="NN" toknums="140" upos="NOUN" wmwe="null" word="cheese" xpos="NN" />
    </node>
    <node ID="0.15" type="Word">
      <attributes paragraph="1" paragraph_position="15" text="for" />
      <extra config="default" deprel="case" depth="6" edeps="17:case" enhanced="17:case" feats="null" features="_" frame="_" gov="134" govlemma="sandwich" head="17" lemma="for" lexcat="P" lexlemma="for" lextag="O-P-p.Purpose" local_gov="8" local_obj="17" local_toknums="15" misc="null" next_terminal_lower_common_ancestor_category="Q" next_terminal_lower_common_ancestor_depth="4" obj="143" objlemma="32" orig_paragraph="1" pos="ADP" remarks="0.141" smwe="null" ss="p.Purpose" ss2="p.Purpose" tag="IN" toknums="141" upos="ADP" wmwe="null" word="for" xpos="IN" />
    </node>
    <node ID="0.16" type="Word">
      <attributes paragraph="1" paragraph_position="16" text="+" />
      <extra deprel="advmod" depth="6" edeps="17:advmod" enhanced="17:advmod" feats="null" features="_" frame="_" head="17" lemma="+" lextag="O-SYM" misc="SpaceAfter=No" next_terminal_lower_common_ancestor_category="Q" next_terminal_lower_common_ancestor_depth="4" orig_paragraph="1" pos="SYM" remarks="0.142" smwe="null" tag="SYM" upos="SYM" wmwe="null" word="+" xpos="SYM" />
    </node>
    <node ID="0.17" type="Word">
      <attributes paragraph="1" paragraph_position="17" text="32" />
      <extra deprel="obl" depth="6" edeps="8:obl:for" enhanced="8:obl:for" feats="NumType=Card" features="NumType=Card" frame="_" head="8" lemma="32" lextag="O-NUM" misc="null" next_terminal_lower_common_ancestor_category="Q" next_terminal_lower_common_ancestor_depth="4" orig_paragraph="1" pos="NUM" remarks="0.143" smwe="null" tag="CD" upos="NUM" wmwe="null" word="32" xpos="CD" />
    </node>
    <node ID="0.18" type="Word">
      <attributes paragraph="1" paragraph_position="18" text="delicious" />
      <extra deprel="amod" depth="7" edeps="17:amod" enhanced="17:amod" feats="Degree=Pos" features="Degree=Pos" frame="_" head="17" lemma="delicious" lextag="O-ADJ" misc="SpaceAfter=No" next_terminal_lower_common_ancestor_category="H" next_terminal_lower_common_ancestor_depth="1" orig_paragraph="1" pos="ADJ" remarks="0.144" smwe="null" tag="JJ" upos="ADJ" wmwe="null" word="delicious" xpos="JJ" />
    </node>
    <node ID="0.19" type="Punctuation">
      <attributes paragraph="1" paragraph_position="19" text="." />
      <extra deprel="punct" depth="3" edeps="2:punct" enhanced="2:punct" feats="null" features="_" frame="_" head="2" lemma="." lextag="O-PUNCT" misc="null" next_terminal_lower_common_ancestor_category="null" next_terminal_lower_common_ancestor_depth="0" orig_paragraph="1" pos="PUNCT" remarks="0.145" smwe="null" tag="." upos="PUNCT" wmwe="null" word="." xpos="." />
    </node>
  </layer>
  <layer layerID="1">
    <attributes />
    <node ID="1.1" type="FN">
      <attributes />
      <edge toID="1.2" type="head">
        <attributes />
        <category tag="head" />
      </edge>
    </node>
    <node ID="1.2" type="FN">
      <attributes />
      <edge toID="1.3" type="head">
        <attributes />
        <category tag="head" />
      </edge>
      <edge toID="1.4" type="nsubj">
        <attributes />
        <category tag="nsubj" />
      </edge>
      <edge toID="1.5" type="obj">
        <attributes />
        <category tag="obj" />
      </edge>
      <edge toID="1.7" type="U">
        <attributes />
        <category tag="U" />
      </edge>
    </node>
    <node ID="1.3" type="FN">
      <attributes />
      <edge toID="0.2" type="Terminal">
        <attributes />
        <category tag="Terminal" />
      </edge>
    </node>
    <node ID="1.4" type="FN">
      <attributes />
      <edge toID="0.1" type="Terminal">
        <attributes />
        <category tag="Terminal" />
      </edge>
    </node>
    <node ID="1.5" type="FN">
      <attributes />
      <edge toID="1.6" type="head">
        <attributes />
        <category tag="head" />
      </edge>
      <edge toID="1.8" type="det">
        <attributes />
        <category tag="det" />
      </edge>
      <edge toID="1.9" type="amod">
        <attributes />
        <category tag="amod" />
      </edge>
      <edge toID="1.10" type="acl">
        <attributes />
        <category tag="acl" />
      </edge>
    </node>
    <node ID="1.6" type="FN">
      <attributes />
      <edge toID="0.5" type="Terminal">
        <attributes />
        <category tag="Terminal" />
      </edge>
    </node>
    <node ID="1.7" type="PNCT">
      <attributes />
      <edge toID="0.19" type="Terminal">
        <attributes />
        <category tag="Terminal" />
      </edge>
    </node>
    <node ID="1.8" type="FN">
      <attributes />
      <edge toID="0.3" type="Terminal">
        <attributes />
        <category tag="Terminal" />
      </edge>
    </node>
    <node ID="1.9" type="FN">
      <attributes />
      <edge toID="0.4" type="Terminal">
        <attributes />
        <category tag="Terminal" />
      </edge>
    </node>
    <node ID="1.10" type="FN">
      <attributes />
      <edge toID="1.11" type="head">
        <attributes />
        <category tag="head" />
      </edge>
      <edge toID="1.12" type="advmod">
        <attributes />
        <category tag="advmod" />
      </edge>
      <edge toID="1.13" type="nsubj">
        <attributes />
        <category tag="nsubj" />
      </edge>
      <edge toID="1.14" type="obj">
        <attributes />
        <category tag="obj" />
      </edge>
      <edge toID="1.16" type="obl">
        <attributes />
        <category tag="obl" />
      </edge>
      <edge toID="1.18" type="obl">
        <attributes />
        <category tag="obl" />
      </edge>
    </node>
    <node ID="1.11" type="FN">
      <attributes />
      <edge toID="0.8" type="Terminal">
        <attributes />
        <category tag="Terminal" />
      </edge>
    </node>
    <node ID="1.12" type="FN">
      <attributes />
      <edge toID="0.6" type="Terminal">
        <attributes />
        <category tag="Terminal" />
      </edge>
    </node>
    <node ID="1.13" type="FN">
      <attributes />
      <edge toID="0.7" type="Terminal">
        <attributes />
        <category tag="Terminal" />
      </edge>
    </node>
    <node ID="1.14" type="FN">
      <attributes />
      <edge toID="1.15" type="head">
        <attributes />
        <category tag="head" />
      </edge>
      <edge toID="1.20" type="det">
        <attributes />
        <category tag="det" />
      </edge>
    </node>
    <node ID="1.15" type="FN">
      <attributes />
      <edge toID="0.10" type="Terminal">
        <attributes />
        <category tag="Terminal" />
      </edge>
    </node>
    <node ID="1.16" type="FN">
      <attributes />
      <edge toID="1.17" type="head">
        <attributes />
        <category tag="head" />
      </edge>
      <edge toID="1.21" type="case">
        <attributes />
        <category tag="case" />
      </edge>
      <edge toID="1.22" type="nmod">
        <attributes />
        <category tag="nmod" />
      </edge>
    </node>
    <node ID="1.17" type="FN">
      <attributes />
      <edge toID="0.12" type="Terminal">
        <attributes />
        <category tag="Terminal" />
      </edge>
    </node>
    <node ID="1.18" type="FN">
      <attributes />
      <edge toID="1.19" type="head">
        <attributes />
        <category tag="head" />
      </edge>
      <edge toID="1.24" type="case">
        <attributes />
        <category tag="case" />
      </edge>
      <edge toID="1.25" type="advmod">
        <attributes />
        <category tag="advmod" />
      </edge>
      <edge toID="1.26" type="amod">
        <attributes />
        <category tag="amod" />
      </edge>
    </node>
    <node ID="1.19" type="FN">
      <attributes />
      <edge toID="0.17" type="Terminal">
        <attributes />
        <category tag="Terminal" />
      </edge>
    </node>
    <node ID="1.20" type="FN">
      <attributes />
      <edge toID="0.9" type="Terminal">
        <attributes />
        <category tag="Terminal" />
      </edge>
    </node>
    <node ID="1.21" type="FN">
      <attributes />
      <edge toID="0.11" type="Terminal">
        <attributes />
        <category tag="Terminal" />
      </edge>
    </node>
    <node ID="1.22" type="FN">
      <attributes />
      <edge toID="1.23" type="head">
        <attributes />
        <category tag="head" />
      </edge>
      <edge toID="1.27" type="case">
        <attributes />
        <category tag="case" />
      </edge>
    </node>
    <node ID="1.23" type="FN">
      <attributes />
      <edge toID="0.14" type="Terminal">
        <attributes />
        <category tag="Terminal" />
      </edge>
    </node>
    <node ID="1.24" type="FN">
      <attributes />
      <edge toID="0.15" type="Terminal">
        <attributes />
        <category tag="Terminal" />
      </edge>
    </node>
    <node ID="1.25" type="FN">
      <attributes />
      <edge toID="0.16" type="Terminal">
        <attributes />
        <category tag="Terminal" />
      </edge>
    </node>
    <node ID="1.26" type="FN">
      <attributes />
      <edge toID="0.18" type="Terminal">
        <attributes />
        <category tag="Terminal" />
      </edge>
    </node>
    <node ID="1.27" type="FN">
      <attributes />
      <edge toID="0.13" type="Terminal">
        <attributes />
        <category tag="Terminal" />
      </edge>
    </node>
  </layer>
</root>
