<root annotationID="0" passageID="reviews-018548-0004">
  <attributes />
  <extra format="conllu" />
  <layer layerID="0">
    <attributes />
    <extra doc="[[[10239237003504588839, 561228191312463089, 13656873538139661788, 94, 0, 2, 426, 1, 4370460163704169311, 5097672513440128799, 10239237003504588839], [2446979777954330933, 15203660437495798636, 13927759927860985106, 99, 0, 2, 8206900633647566924, 0, 13110060611322374290, 16978132545290669629, 7880491877800203539], [18194338103975822726, 18194338103975822726, 1292078113972184607, 84, 0, 2, 420, 2, 13110060611322374290, 2985121464356781022, 11402152577528684049], [10239237003504588839, 561228191312463089, 13656873538139661788, 94, 0, 2, 426, 1, 4370460163704169311, 5097672513440128799, 10239237003504588839], [16978132545290669629, 16978132545290669629, 13927759927860985106, 99, 0, 2, 405, -3, 11123243248953317070, 16978132545290669629, 16978132545290669629], [16702533373841340275, 5379644128261274187, 272890857012483650, 83, 0, 2, 395, -1, 13110060611322374290, 15817570140490810055, 14983792334920777924], [12286903790479710773, 12286903790479710773, 164681854541413346, 85, 0, 2, 397, -2, 4088098365541558500, 15369245168918225700, 12286903790479710773], [2593208677638477497, 2593208677638477497, 2593208677638477497, 96, 0, 2, 442, -6, 2593208677638477497, 2593208677638477497, 2593208677638477497], [14560795576765492085, 14560795576765492085, 17571114184892886314, 88, 0, 2, 404, -7, 4088098365541558500, 15598372446745583797, 14560795576765492085], [10239237003504588839, 561228191312463089, 13656873538139661788, 94, 0, 2, 426, 1, 4370460163704169311, 5097672513440128799, 10239237003504588839], [16978132545290669629, 16978132545290669629, 13927759927860985106, 99, 0, 2, 407, -9, 11123243248953317070, 16978132545290669629, 16978132545290669629], [3225287980215270582, 3225287980215270582, 164681854541413346, 85, 0, 2, 397, -1, 13110060611322374290, 8861071527689086543, 12215235795949914907], [447765159362469301, 447765159362469301, 164681854541413346, 85, 0, 2, 422, -2, 4088098365541558500, 13210364986222294696, 447765159362469301], [12646065887601541794, 12646065887601541794, 12646065887601541794, 96, 0, 2, 442, -3, 12646065887601541794, 12646065887601541794, 12646065887601541794]]]" />
    <node ID="0.1" type="Word">
      <attributes paragraph="1" paragraph_position="1" text="it" />
      <extra deprel="expl" edeps="2:expl" enhanced="2:expl" feats="Case=Nom|Gender=Neut|Number=Sing|Person=3|PronType=Prs" features="Case=Nom|Gender=Neut|Number=Sing|Person=3|PronType=Prs" frame="_" head="2" lemma="it" lextag="O-PRON" misc="null" orig_paragraph="1" pos="PRON" remarks="0.32" smwe="null" tag="PRP" upos="PRON" wmwe="null" word="it" xpos="PRP" />
    </node>
    <node ID="0.2" type="Word">
      <attributes paragraph="1" paragraph_position="2" text="seems" />
      <extra deprel="root" edeps="0:root" enhanced="0:root" feats="Mood=Ind|Number=Sing|Person=3|Tense=Pres|VerbForm=Fin" features="Mood=Ind|Number=Sing|Person=3|Tense=Pres|VerbForm=Fin" frame="_" head="0" lemma="seem" lexcat="V" lexlemma="seem" lextag="O-V-v.cognition" local_toknums="2" misc="null" orig_paragraph="1" pos="VERB" remarks="0.33" smwe="null" ss="v.cognition" ss2="null" tag="VBZ" toknums="33" upos="VERB" wmwe="null" word="seems" xpos="VBZ" />
    </node>
    <node ID="0.3" type="Word">
      <attributes paragraph="1" paragraph_position="3" text="like" />
      <extra config="subordinating" deprel="mark" edeps="6:mark" enhanced="6:mark" feats="null" features="_" frame="_" gov="33" govlemma="seem" head="6" lemma="like" lexcat="P" lexlemma="like" lextag="O-P-p.Theme|p.ComparisonRef" local_gov="2" local_obj="5" local_toknums="3" misc="null" obj="36" objlemma="be" orig_paragraph="1" pos="SCONJ" remarks="0.34" smwe="null" ss="p.Theme" ss2="p.ComparisonRef" tag="IN" toknums="34" upos="SCONJ" wmwe="null" word="like" xpos="IN" />
    </node>
    <node ID="0.4" type="Word">
      <attributes paragraph="1" paragraph_position="4" text="it" />
      <extra deprel="nsubj" edeps="6:nsubj" enhanced="6:nsubj" feats="Case=Nom|Gender=Neut|Number=Sing|Person=3|PronType=Prs" features="Case=Nom|Gender=Neut|Number=Sing|Person=3|PronType=Prs" frame="_" head="6" lemma="it" lextag="O-PRON" misc="SpaceAfter=No" orig_paragraph="1" pos="PRON" remarks="0.35" smwe="null" tag="PRP" upos="PRON" wmwe="null" word="it" xpos="PRP" />
    </node>
    <node ID="0.5" type="Word">
      <attributes paragraph="1" paragraph_position="5" text="s" />
      <extra deprel="cop" edeps="6:cop" enhanced="6:cop" feats="Mood=Ind|Number=Sing|Person=3|Tense=Pres|VerbForm=Fin" features="Mood=Ind|Number=Sing|Person=3|Tense=Pres|VerbForm=Fin" frame="_" head="6" lemma="be" lexcat="V" lexlemma="be" lextag="O-V-v.stative" local_toknums="5" misc="null" orig_paragraph="1" pos="AUX" remarks="0.36" smwe="null" ss="v.stative" ss2="null" tag="VBZ" toknums="36" upos="AUX" wmwe="null" word="s" xpos="VBZ" />
    </node>
    <node ID="0.6" type="Word">
      <attributes paragraph="1" paragraph_position="6" text="healthier" />
      <extra deprel="advcl" edeps="2:advcl:like" enhanced="2:advcl:like" feats="Degree=Cmp" features="Degree=Cmp" frame="_" head="2" lemma="healthier" lextag="O-ADJ" misc="null" orig_paragraph="1" pos="ADJ" remarks="0.37" smwe="null" tag="JJR" upos="ADJ" wmwe="null" word="healthier" xpos="JJR" />
    </node>
    <node ID="0.7" type="Word">
      <attributes paragraph="1" paragraph_position="7" text="too" />
      <extra deprel="advmod" edeps="2:advmod" enhanced="2:advmod" feats="null" features="_" frame="_" head="2" lemma="too" lextag="O-ADV" misc="SpaceAfter=No" orig_paragraph="1" pos="ADV" remarks="0.38" smwe="null" tag="RB" upos="ADV" wmwe="null" word="too" xpos="RB" />
    </node>
    <node ID="0.8" type="Punctuation">
      <attributes paragraph="1" paragraph_position="8" text="," />
      <extra deprel="punct" edeps="12:punct" enhanced="12:punct" feats="null" features="_" frame="_" head="12" lemma="," lextag="O-PUNCT" misc="null" orig_paragraph="1" pos="PUNCT" remarks="0.39" smwe="null" tag="," upos="PUNCT" wmwe="null" word="," xpos="," />
    </node>
    <node ID="0.9" type="Word">
      <attributes paragraph="1" paragraph_position="9" text="but" />
      <extra deprel="cc" edeps="12:cc" enhanced="12:cc" feats="null" features="_" frame="_" head="12" lemma="but" lextag="O-CCONJ" misc="null" orig_paragraph="1" pos="CCONJ" remarks="0.4" smwe="null" tag="CC" upos="CCONJ" wmwe="null" word="but" xpos="CC" />
    </node>
    <node ID="0.10" type="Word">
      <attributes paragraph="1" paragraph_position="10" text="it" />
      <extra deprel="nsubj" edeps="12:nsubj" enhanced="12:nsubj" feats="Case=Nom|Gender=Neut|Number=Sing|Person=3|PronType=Prs" features="Case=Nom|Gender=Neut|Number=Sing|Person=3|PronType=Prs" frame="_" head="12" lemma="it" lextag="O-PRON" misc="SpaceAfter=No" orig_paragraph="1" pos="PRON" remarks="0.41" smwe="null" tag="PRP" upos="PRON" wmwe="null" word="it" xpos="PRP" />
    </node>
    <node ID="0.11" type="Word">
      <attributes paragraph="1" paragraph_position="11" text="s" />
      <extra deprel="cop" edeps="12:cop" enhanced="12:cop" feats="Mood=Ind|Number=Sing|Person=3|Tense=Pres|VerbForm=Fin" features="Mood=Ind|Number=Sing|Person=3|Tense=Pres|VerbForm=Fin" frame="_" head="12" lemma="be" lexcat="V" lexlemma="be" lextag="O-V-v.stative" local_toknums="11" misc="null" orig_paragraph="1" pos="AUX" remarks="0.42" smwe="null" ss="v.stative" ss2="null" tag="VBZ" toknums="42" upos="AUX" wmwe="null" word="s" xpos="VBZ" />
    </node>
    <node ID="0.12" type="Word">
      <attributes paragraph="1" paragraph_position="12" text="prolly" />
      <extra deprel="conj" edeps="2:conj:but" enhanced="2:conj:but" feats="null" features="_" frame="_" head="2" lemma="prolly" lextag="O-ADV" misc="null" orig_paragraph="1" pos="ADV" remarks="0.43" smwe="null" tag="RB" upos="ADV" wmwe="null" word="prolly" xpos="RB" />
    </node>
    <node ID="0.13" type="Word">
      <attributes paragraph="1" paragraph_position="13" text="not" />
      <extra deprel="advmod" edeps="12:advmod" enhanced="12:advmod" feats="null" features="_" frame="_" head="12" lemma="not" lextag="O-ADV" misc="SpaceAfter=No" orig_paragraph="1" pos="PART" remarks="0.44" smwe="null" tag="RB" upos="PART" wmwe="null" word="not" xpos="RB" />
    </node>
    <node ID="0.14" type="Punctuation">
      <attributes paragraph="1" paragraph_position="14" text="." />
      <extra deprel="punct" edeps="2:punct" enhanced="2:punct" feats="null" features="_" frame="_" head="2" lemma="." lextag="O-PUNCT" misc="null" orig_paragraph="1" pos="PUNCT" remarks="0.45" smwe="null" tag="." upos="PUNCT" wmwe="null" word="." xpos="." />
    </node>
  </layer>
  <layer layerID="1">
    <attributes />
    <node ID="1.1" type="FN">
      <attributes />
      <edge toID="1.2" type="head">
        <attributes />
        <category tag="head" />
      </edge>
      <edge toID="1.4" type="mark">
        <attributes />
        <category tag="mark" />
      </edge>
      <edge toID="1.5" type="advcl">
        <attributes />
        <category tag="advcl" />
      </edge>
      <edge toID="1.7" type="cc">
        <attributes />
        <category tag="cc" />
      </edge>
      <edge toID="1.8" type="conj">
        <attributes />
        <category tag="conj" />
      </edge>
    </node>
    <node ID="1.2" type="FN">
      <attributes />
      <edge toID="1.3" type="head">
        <attributes />
        <category tag="head" />
      </edge>
      <edge toID="1.10" type="expl">
        <attributes />
        <category tag="expl" />
      </edge>
      <edge toID="1.13" type="advmod">
        <attributes />
        <category tag="advmod" />
      </edge>
      <edge toID="1.18" type="U">
        <attributes />
        <category tag="U" />
      </edge>
    </node>
    <node ID="1.3" type="FN">
      <attributes />
      <edge toID="0.2" type="Terminal">
        <attributes />
        <category tag="Terminal" />
      </edge>
    </node>
    <node ID="1.4" type="FN">
      <attributes />
      <edge toID="0.3" type="Terminal">
        <attributes />
        <category tag="Terminal" />
      </edge>
    </node>
    <node ID="1.5" type="FN">
      <attributes />
      <edge toID="1.6" type="head">
        <attributes />
        <category tag="head" />
      </edge>
      <edge toID="1.11" type="nsubj">
        <attributes />
        <category tag="nsubj" />
      </edge>
      <edge toID="1.12" type="cop">
        <attributes />
        <category tag="cop" />
      </edge>
    </node>
    <node ID="1.6" type="FN">
      <attributes />
      <edge toID="0.6" type="Terminal">
        <attributes />
        <category tag="Terminal" />
      </edge>
    </node>
    <node ID="1.7" type="FN">
      <attributes />
      <edge toID="0.9" type="Terminal">
        <attributes />
        <category tag="Terminal" />
      </edge>
    </node>
    <node ID="1.8" type="FN">
      <attributes />
      <edge toID="1.9" type="head">
        <attributes />
        <category tag="head" />
      </edge>
      <edge toID="1.14" type="U">
        <attributes />
        <category tag="U" />
      </edge>
      <edge toID="1.15" type="nsubj">
        <attributes />
        <category tag="nsubj" />
      </edge>
      <edge toID="1.16" type="cop">
        <attributes />
        <category tag="cop" />
      </edge>
      <edge toID="1.17" type="advmod">
        <attributes />
        <category tag="advmod" />
      </edge>
    </node>
    <node ID="1.9" type="FN">
      <attributes />
      <edge toID="0.12" type="Terminal">
        <attributes />
        <category tag="Terminal" />
      </edge>
    </node>
    <node ID="1.10" type="FN">
      <attributes />
      <edge toID="0.1" type="Terminal">
        <attributes />
        <category tag="Terminal" />
      </edge>
    </node>
    <node ID="1.11" type="FN">
      <attributes />
      <edge toID="0.4" type="Terminal">
        <attributes />
        <category tag="Terminal" />
      </edge>
    </node>
    <node ID="1.12" type="FN">
      <attributes />
      <edge toID="0.5" type="Terminal">
        <attributes />
        <category tag="Terminal" />
      </edge>
    </node>
    <node ID="1.13" type="FN">
      <attributes />
      <edge toID="0.7" type="Terminal">
        <attributes />
        <category tag="Terminal" />
      </edge>
    </node>
    <node ID="1.14" type="PNCT">
      <attributes />
      <edge toID="0.8" type="Terminal">
        <attributes />
        <category tag="Terminal" />
      </edge>
    </node>
    <node ID="1.15" type="FN">
      <attributes />
      <edge toID="0.10" type="Terminal">
        <attributes />
        <category tag="Terminal" />
      </edge>
    </node>
    <node ID="1.16" type="FN">
      <attributes />
      <edge toID="0.11" type="Terminal">
        <attributes />
        <category tag="Terminal" />
      </edge>
    </node>
    <node ID="1.17" type="FN">
      <attributes />
      <edge toID="0.13" type="Terminal">
        <attributes />
        <category tag="Terminal" />
      </edge>
    </node>
    <node ID="1.18" type="PNCT">
      <attributes />
      <edge toID="0.14" type="Terminal">
        <attributes />
        <category tag="Terminal" />
      </edge>
    </node>
  </layer>
</root>
