<root annotationID="0" passageID="101972_0006_22-22">
  <attributes />
  <layer layerID="0">
    <attributes />
    <node ID="0.1" type="Word">
      <attributes paragraph="1" paragraph_position="1" text="paraded" />
      <extra deprel="ccomp" edeps="13:ccomp" feats="Tense=Past|VerbForm=Part" head="13" identified_for_pss="0" ind="20" is_part_of_mwe="False" lemma="parade" lexcat="V" lexlemma="parade" lextag="O-V-v.motion" misc="null" smwe="null" upos="VERB" wmwe="null" word="paraded" xpos="VBN" />
    </node>
    <node ID="0.2" type="Word">
      <attributes paragraph="1" paragraph_position="2" text="without" />
      <extra config="subordinating" deprel="mark" edeps="23:mark" feats="null" gov="67" govlemma="parade" head="23" identified_for_pss="1" ind="22" is_part_of_mwe="False" lemma="without" lexcat="P" lexlemma="without" lextag="O-P-p.Manner" local_gov="20" local_obj="23" misc="null" obj="70" objlemma="sign" smwe="null" upos="SCONJ" wmwe="null" word="without" xpos="IN" />
    </node>
    <node ID="0.3" type="Word">
      <attributes paragraph="1" paragraph_position="3" text="signing" />
      <extra deprel="advcl" edeps="20:advcl" feats="VerbForm=Ger" head="20" identified_for_pss="0" ind="23" is_part_of_mwe="False" lemma="sign" lexcat="V" lexlemma="sign" lextag="B-V-v.communication" misc="null" smwe="null" upos="VERB" wmwe="[2, 1]" word="signing" xpos="VBG" />
    </node>
  </layer>
  <layer layerID="1">
    <attributes />
    <node ID="1.1" type="FN">
      <attributes />
      <edge toID="1.2" type="H">
        <attributes />
        <category tag="H" />
      </edge>
    </node>
    <node ID="1.2" type="FN">
      <attributes />
      <edge toID="1.3" type="gov">
        <attributes />
        <category tag="gov" />
      </edge>
      <edge toID="1.4" type="p.Manner">
        <attributes />
        <category tag="p.Manner" />
      </edge>
      <edge toID="1.5" type="obj">
        <attributes />
        <category tag="obj" />
      </edge>
    </node>
    <node ID="1.3" type="FN">
      <attributes />
      <edge toID="0.1" type="Terminal">
        <attributes />
        <category tag="Terminal" />
      </edge>
    </node>
    <node ID="1.4" type="FN">
      <attributes />
      <edge toID="0.2" type="Terminal">
        <attributes />
        <category tag="Terminal" />
      </edge>
    </node>
    <node ID="1.5" type="FN">
      <attributes />
      <edge toID="0.3" type="Terminal">
        <attributes />
        <category tag="Terminal" />
      </edge>
    </node>
  </layer>
</root>
