<root annotationID="0" passageID="210066008">
  <attributes annotationID="1853" passageID="352" remarks="26243" userID="14" />
  <layer layerID="0">
    <attributes />
    <extra doc="[[]]" />
    <node ID="0.1" type="Word">
      <attributes paragraph="1" paragraph_position="1" text="Are" />
      <extra deprel="cop" edeps="3:cop" feats="Mood=Ind|Tense=Pres|VerbForm=Fin" head="3" lemma="be" lextag="O-V-v.stative" misc="null" orig_paragraph="1" remarks="0.142" smwe="null" upos="AUX" wmwe="null" word="Are" xpos="VBP" />
    </node>
    <node ID="0.2" type="Word">
      <attributes paragraph="1" paragraph_position="2" text="they" />
      <extra deprel="nsubj" edeps="3:nsubj" feats="Case=Nom|Number=Plur|Person=3|PronType=Prs" head="3" lemma="they" lextag="O-PRON" misc="null" orig_paragraph="1" remarks="0.143" smwe="null" upos="PRON" wmwe="null" word="they" xpos="PRP" />
    </node>
    <node ID="0.3" type="Word">
      <attributes paragraph="1" paragraph_position="3" text="serious" />
      <extra deprel="root" edeps="0:root" feats="Degree=Pos" head="0" lemma="serious" lextag="O-ADJ" misc="SpaceAfter=No" orig_paragraph="1" remarks="0.144" smwe="null" upos="ADJ" wmwe="null" word="serious" xpos="JJ" />
    </node>
    <node ID="0.4" type="Punctuation">
      <attributes paragraph="1" paragraph_position="4" text="?" />
      <extra deprel="punct" edeps="3:punct" feats="null" head="3" lemma="?" lextag="O-PUNCT" misc="null" orig_paragraph="1" remarks="0.145" smwe="null" upos="PUNCT" wmwe="null" word="?" xpos="." />
    </node>
  </layer>
  <layer layerID="1">
    <attributes />
    <node ID="1.1" type="FN">
      <attributes />
      <extra remarks="1.1" />
      <edge toID="1.2" type="H">
        <attributes />
        <category tag="H" />
      </edge>
      <edge toID="1.3" type="U">
        <attributes />
        <category tag="U" />
      </edge>
    </node>
    <node ID="1.2" type="FN">
      <attributes />
      <extra remarks="1.192" />
      <edge toID="1.4" type="F">
        <attributes />
        <category tag="F" />
      </edge>
      <edge toID="1.5" type="A">
        <attributes />
        <category tag="A" />
      </edge>
      <edge toID="1.6" type="S">
        <attributes />
        <category tag="S" />
      </edge>
    </node>
    <node ID="1.3" type="PNCT">
      <attributes />
      <extra remarks="1.280" />
      <edge toID="0.4" type="Terminal">
        <attributes />
        <category tag="Terminal" />
      </edge>
    </node>
    <node ID="1.4" type="FN">
      <attributes />
      <extra remarks="1.193" />
      <edge toID="0.1" type="Terminal">
        <attributes />
        <category tag="Terminal" />
      </edge>
    </node>
    <node ID="1.5" type="FN">
      <attributes />
      <extra remarks="1.194" />
      <edge toID="0.2" type="Terminal">
        <attributes />
        <category tag="Terminal" />
      </edge>
    </node>
    <node ID="1.6" type="FN">
      <attributes />
      <extra remarks="1.195" />
      <edge toID="0.3" type="Terminal">
        <attributes />
        <category tag="Terminal" />
      </edge>
    </node>
  </layer>
</root>
